sshared/__init__.py
sshared/retry.py
sshared/strict_struct.py
sshared/time.py
sshared/word_split.py
sshared/api/__init__.py
sshared/api/exception_handlers.py
sshared/api/handler_spec.py
sshared/api/lifespans.py
sshared/api/openapi.py
sshared/api/response.py
sshared/api/state.py
sshared/api/structs.py
sshared/api/uvicorn.py
sshared/config/__init__.py
sshared/config/blocks.py
sshared/logging/__init__.py
sshared/logging/config.py
sshared/logging/logger.py
sshared/logging/record.py
sshared/logging/types.py
sshared/postgres/__init__.py
sshared/postgres/connection_manager.py
sshared/postgres/json.py
sshared/postgres/materialized_view.py
sshared/postgres/pool.py
sshared/postgres/table.py
sshared/postgres/view.py
sshared/terminal/color.py
sshared/terminal/exception.py
sshared-0.21.0.dist-info/METADATA
sshared-0.21.0.dist-info/WHEEL
sshared-0.21.0.dist-info/licenses/LICENSE
sshared-0.21.0.dist-info/RECORD
