Metadata-Version: 2.4
Name: sshared
Version: 0.21.0
Summary: 后端共享组件
Author-email: FHU-yezi <yehaowei20060411@qq.com>
License: MIT License
License-File: LICENSE
Classifier: Development Status :: 4 - Beta
Classifier: License :: OSI Approved :: MIT License
Classifier: Programming Language :: Python :: 3 :: Only
Classifier: Typing :: Typed
Requires-Python: >=3.9
Requires-Dist: msgspec>=0.19.0
Provides-Extra: api
Requires-Dist: litestar>=2.14.0; extra == 'api'
Provides-Extra: config
Requires-Dist: tomli>=2.0.0; extra == 'config'
Provides-Extra: postgres
Requires-Dist: psycopg[binary]>=3.2.0; extra == 'postgres'
Provides-Extra: retry
Requires-Dist: typing-extensions>=4.12.0; extra == 'retry'
